pyknos/__init__.py
pyknos/__version__.py
pyknos/mdn/__init__.py
pyknos/mdn/mdn.py
pyknos/nflows/__init__.py
pyknos/nflows/distributions/__init__.py
pyknos/nflows/flows/__init__.py
pyknos/nflows/nn/__init__.py
pyknos/nflows/nn/nde/__init__.py
pyknos/nflows/nn/nets/__init__.py
pyknos/nflows/transforms/__init__.py
pyknos/nflows/transforms/splines/__init__.py
pyknos/nflows/utils/__init__.py
pyknos-0.16.0.dist-info/LICENSE.txt
pyknos-0.16.0.dist-info/METADATA
pyknos-0.16.0.dist-info/WHEEL
pyknos-0.16.0.dist-info/top_level.txt
pyknos-0.16.0.dist-info/RECORD
