Metadata-Version: 2.1
Name: pyknos
Version: 0.16.0
Summary: don't regress. A package for neural conditional density estimation.
Author-email: sbi-dev <simulation.based.inference@gmail.com>
Project-URL: source, https://github.com/sbi-dev/pyknos
Project-URL: tracker, https://github.com/sbi-dev/pyknos/issues
Keywords: conditional density estimation,mixture density networks,normalizing flows,diffusion models,PyTorch
Classifier: Intended Audience :: Developers
Classifier: Intended Audience :: Education
Classifier: Intended Audience :: Science/Research
Classifier: Topic :: Adaptive Technologies
Classifier: Topic :: Scientific/Engineering
Classifier: Topic :: Scientific/Engineering :: Artificial Intelligence
Classifier: Topic :: Scientific/Engineering :: Mathematics
Classifier: License :: OSI Approved :: GNU Affero General Public License v3 or later
Classifier: Natural Language :: English
Classifier: Operating System :: OS Independent
Classifier: Programming Language :: Python :: 3
Classifier: Development Status :: 3 - Alpha
Requires-Python: >=3.8
License-File: LICENSE.txt
Requires-Dist: matplotlib
Requires-Dist: nflows==0.14
Requires-Dist: numpy
Requires-Dist: tensorboard
Requires-Dist: torch
Requires-Dist: tqdm
Provides-Extra: dev
Requires-Dist: jupyter; extra == "dev"
Requires-Dist: nbconvert; extra == "dev"
Requires-Dist: pre-commit==3.5.0; extra == "dev"
Requires-Dist: pyyaml; extra == "dev"
Requires-Dist: pyright; extra == "dev"
Requires-Dist: ruff>=0.3.3; extra == "dev"
Requires-Dist: pytest; extra == "dev"
Requires-Dist: pytest-cov; extra == "dev"
Requires-Dist: pytest-xdist; extra == "dev"
Requires-Dist: torchtestcase; extra == "dev"
